{
  "project_info": {
    "project_number": "1050335747127",
    "project_id": "flutter-chat-app-9fef0",
    "storage_bucket": "flutter-chat-app-9fef0.firebasestorage.app"
  },
  "client": [
    {
      "client_info": {
        "mobilesdk_app_id": "1:1050335747127:android:9d08a3b3d4a158c4d0b3b2",
        "android_client_info": {
          "package_name": "com.technicalencoder.chatapp"
        }
      },
      "oauth_client": [],
      "api_key": [
        {
          "current_key": "AIzaSyCUWcXiqS6t0qc9nBIitRWHI28dYniQXCg"
        }
      ],
      "services": {
        "appinvite_service": {
          "other_platform_oauth_client": []
        }
      }
    }
  ],
  "configuration_version": "1"
}